license.txt
setup.py
PyMGA/__init__.py
PyMGA.egg-info/PKG-INFO
PyMGA.egg-info/SOURCES.txt
PyMGA.egg-info/dependency_links.txt
PyMGA.egg-info/not-zip-safe
PyMGA.egg-info/requires.txt
PyMGA.egg-info/top_level.txt
PyMGA/cases/__init__.py
PyMGA/cases/pypsa_testcase.py
PyMGA/cases/pypsa_to_case.py
PyMGA/cases/solutions.py
PyMGA/cases/testcases.py
PyMGA/methods/MAA.py
PyMGA/methods/MGA.py
PyMGA/methods/__init__.py
PyMGA/methods/bMAA.py
PyMGA/sampler/__init__.py
PyMGA/sampler/sampler.py
PyMGA/utilities/__init__.py
PyMGA/utilities/dask_helpers.py
PyMGA/utilities/general.py
PyMGA/utilities/plot.py
PyMGA/utilities/solve_network.py